plainsight
