Metadata-Version: 1.1
Name: Plainsight
Version: 1.1.1
Summary: A textual steganography tool to defeat censorship.
Home-page: http://github.com/rw/plainsight
Author: Robert Winslow
Author-email: robert.winslow@gmail.com
License: UNKNOWN
Platform: UNKNOWN
Classifier: Development Status :: 4 - Beta
Classifier: Intended Audience :: Developers
Classifier: Intended Audience :: End Users/Desktop
Classifier: Natural Language :: English
Classifier: Programming Language :: Python
Classifier: Topic :: Security :: Cryptography
Classifier: Topic :: Text Processing :: Filters
Classifier: Topic :: Text Processing :: Linguistic
Requires: argparse
Requires: bitstring
Requires: progressbar
